.coveragerc
.gitignore
.travis.yml
.zerotk.uniform.yml
LICENSE
LICENSE.txt
README.md
pytest.ini
requirements.txt
setup.cfg
setup.py
tasks.py
docs/examples/hello.py_
docs/examples/hello2.py_
tests/test_clikit_app.py
tests/test_clikit_command.py
tests/test_clikit_console.py
tests/test_text.py
zerotk/__init__.py
zerotk/pushpop.py
zerotk/text.py
zerotk.clikit.egg-info/PKG-INFO
zerotk.clikit.egg-info/SOURCES.txt
zerotk.clikit.egg-info/dependency_links.txt
zerotk.clikit.egg-info/namespace_packages.txt
zerotk.clikit.egg-info/requires.txt
zerotk.clikit.egg-info/top_level.txt
zerotk/clikit/__init__.py
zerotk/clikit/app.py
zerotk/clikit/command.py
zerotk/clikit/console.py