Metadata-Version: 1.1
Name: zerotk.clikit
Version: 0.2.0
Summary: A modern Command Line Interface library.
Home-page: https://github.com/zerotk/clikit
Author: Alexandre Andrade
Author-email: kaniabi@gmail.com
License: UNKNOWN
Keywords: command line,cli
Platform: UNKNOWN
Classifier: Development Status :: 4 - Beta
Classifier: Intended Audience :: Developers
Classifier: Topic :: Software Development :: Libraries :: Python Modules
Classifier: License :: OSI Approved :: GNU General Public License v3 (GPLv3)
Classifier: Programming Language :: Python :: 2
Classifier: Programming Language :: Python :: 2.7
Classifier: Programming Language :: Python :: 3
Classifier: Programming Language :: Python :: 3.5
